data_save/funcs.json
data_save/vector_database/docstore.json
data_save/vector_database/graph_store.json
data_save/vector_database/index_store.json
data_save/vector_database/vector_store.json
gpttrace/GPTtrace.py
gpttrace/__init__.py
gpttrace/__main__.py
gpttrace/cmd.py
gpttrace/config.py
gpttrace/execute.py
gpttrace/generate.py
gpttrace/utils/__init__.py
gpttrace/utils/common.py
gpttrace/utils/prompt.py
gpttrace-0.1.2.dist-info/METADATA
gpttrace-0.1.2.dist-info/WHEEL
gpttrace-0.1.2.dist-info/entry_points.txt
gpttrace-0.1.2.dist-info/licenses/LICENSE
gpttrace-0.1.2.dist-info/RECORD
