Metadata-Version: 2.1
Name: gpttrace
Version: 0.1.2
Summary: Generate eBPF programs and tracing with ChatGPT and natural language.
Project-URL: homepage, https://github.com/eunomia-bpf/GPTtrace
Project-URL: repository, https://github.com/eunomia-bpf/GPTtrace
Project-URL: documentation, https://github.com/eunomia-bpf/GPTtrace/blob/main/README.md
Author-email: eunomia-bpf <2629757717@qq.com>
License-Expression: MIT
License-File: LICENSE
Keywords: cli,gpt,openai,productivity,shell
Classifier: Intended Audience :: Developers
Classifier: Intended Audience :: Information Technology
Classifier: Intended Audience :: System Administrators
Classifier: License :: OSI Approved :: MIT License
Classifier: Operating System :: OS Independent
Classifier: Programming Language :: Python :: 3 :: Only
Classifier: Programming Language :: Python :: 3.6
Classifier: Programming Language :: Python :: 3.7
Classifier: Programming Language :: Python :: 3.8
Classifier: Programming Language :: Python :: 3.9
Classifier: Programming Language :: Python :: 3.10
Classifier: Programming Language :: Python :: 3.11
Classifier: Topic :: Software Development
Requires-Python: >=3.6
Requires-Dist: click>=8.1.4
Requires-Dist: langchain>=0.0.227
Requires-Dist: llama-index>=0.7.3
Requires-Dist: marko>=2.0.0
Requires-Dist: openai>=0.27.8
Requires-Dist: prompt-toolkit>=3.0.38
Requires-Dist: pygments-markdown-lexer>=0.1.0.dev39
Requires-Dist: pygments>=2.15.1
